{"www.att.com": "prod-www.zr-att.com.akadns.net", "prod-www.zr-att.com.akadns.net": "www.att.com.edgekey.net", "www.att.com.edgekey.net": "e11697.dscx.akamaiedge.net", "e11697.dscx.akamaiedge.net": "", "adobedc.demdex.net": "demdex.net.ssl.sc.omtrdc.net", "demdex.net.ssl.sc.omtrdc.net": "", "dpm.demdex.net": "gslb-2.demdex.net", "gslb-2.demdex.net": "edge-irl1.demdex.net", "edge-irl1.demdex.net": "dcs-public-edge-irl1-150041215.eu-west-1.elb.amazonaws.com", "dcs-public-edge-irl1-150041215.eu-west-1.elb.amazonaws.com": "", "cdn.quantummetric.com": "", "s2.go-mpulse.net": "ip46s2.go-mpulse.net.edgekey.net", "ip46s2.go-mpulse.net.edgekey.net": "e9858.dscx.akamaiedge.net", "e9858.dscx.akamaiedge.net": "", "smetrics.att.com": "smetrics.att.com.edgekey.net", "smetrics.att.com.edgekey.net": "e11697.x.akamaiedge.net", "e11697.x.akamaiedge.net": "", "c.go-mpulse.net": "wildcard46.go-mpulse.net.edgekey.net", "wildcard46.go-mpulse.net.edgekey.net": "e4518.dscapi7.akamaiedge.net", "e4518.dscapi7.akamaiedge.net": "", "attservicesinc.tt.omtrdc.net": "adobetarget.data.adobedc.net", "adobetarget.data.adobedc.net": "", "fls.doubleclick.net": "", "www.google.com": "", "www.gstatic.com": "", "ingest.quantummetric.com": "", "assets.adobetarget.com": "assets.adobetarget.com.edgekey.net", "assets.adobetarget.com.edgekey.net": "e10573.dscf.akamaiedge.net", "e10573.dscf.akamaiedge.net": "", "www.googletagmanager.com": "", "att-sync.quantummetric.com": "", "www.googleadservices.com": "", "googleads.g.doubleclick.net": "", "6100125.fls.doubleclick.net": "dart.l.doubleclick.net", "dart.l.doubleclick.net": "", "ad.doubleclick.net": "", "bat.bing.com": "bat-bing-com.dual-a-0034.a-msedge.net", "bat-bing-com.dual-a-0034.a-msedge.net": "dual-a-0034.a-msedge.net", "dual-a-0034.a-msedge.net": "", "gateway.foresee.com": "d279u996ipxqqp.cloudfront.net", "d279u996ipxqqp.cloudfront.net": "", "connect.facebook.net": "scontent.xx.fbcdn.net", "scontent.xx.fbcdn.net": "", "solutions.invocacdn.com": "d1vb8d7cedz7p0.cloudfront.net", "d1vb8d7cedz7p0.cloudfront.net": "", "servedby.flashtalking.com": "servedby.flashtalking.com-v1.edgekey.net", "servedby.flashtalking.com-v1.edgekey.net": "e4751.b.akamaiedge.net", "e4751.b.akamaiedge.net": "", "brain.foresee.com": "ab1cbac537de54f43b214b172032a880-1825732961.us-east-1.elb.amazonaws.com", "ab1cbac537de54f43b214b172032a880-1825732961.us-east-1.elb.amazonaws.com": "", "pnapi.invoca.net": "pnapi-stateless-868251922.us-east-1.elb.amazonaws.com", "pnapi-stateless-868251922.us-east-1.elb.amazonaws.com": "", "www.facebook.com": "star-mini.c10r.facebook.com", "star-mini.c10r.facebook.com": "", "fid.agkn.com": "fabrick.agkn.com", "fabrick.agkn.com": "", "google.com": "", "aiq-in.att.com": "aiq-in.att.com.edgekey.net", "aiq-in.att.com.edgekey.net": "e11697.dscx.akamaiedge.net", "media-us2.digital.nuance.com": "media-dnc-us2.azureedge.net", "media-dnc-us2.azureedge.net": "media-dnc-us2.afd.azureedge.net", "media-dnc-us2.afd.azureedge.net": "azureedge-t-prod.trafficmanager.net", "azureedge-t-prod.trafficmanager.net": "shed.dual-low.s-part-0017.t-0009.t-msedge.net", "shed.dual-low.s-part-0017.t-0009.t-msedge.net": "azurefd-t-fb-prod.trafficmanager.net", "azurefd-t-fb-prod.trafficmanager.net": "dual.s-part-0017.t-0009.fb-t-msedge.net", "dual.s-part-0017.t-0009.fb-t-msedge.net": "s-part-0017.t-0009.fb-t-msedge.net", "s-part-0017.t-0009.fb-t-msedge.net": "", "securepubads.g.doubleclick.net": "", "att.inq.com": "ts-us2.inq.com", "ts-us2.inq.com": "ts-inq-us2.trafficmanager.net", "ts-inq-us2.trafficmanager.net": "ts-inq-us2.eastus2.cloudapp.azure.com", "ts-inq-us2.eastus2.cloudapp.azure.com": "", "pagead2.googlesyndication.com": "", "40ca21a37e12901a27b330b1eb907500.safeframe.googlesyndication.com": "pagead-googlehosted.l.google.com", "pagead-googlehosted.l.google.com": "", "tpc.googlesyndication.com": "", "d.agkn.com": "data.agkn.com", "data.agkn.com": "tag-terraform-elb-1705565586.eu-central-1.elb.amazonaws.com", "tag-terraform-elb-1705565586.eu-central-1.elb.amazonaws.com": "", "cobrowse-att.inq.com": "cobrowse-us2.inq.com", "cobrowse-us2.inq.com": "cob-inq-us2.trafficmanager.net", "cob-inq-us2.trafficmanager.net": "cob-inq-us2.eastus2.cloudapp.azure.com", "cob-inq-us2.eastus2.cloudapp.azure.com": "", "dynatrace.att.com": "dt-appgw-prod.eastus2.cloudapp.azure.com", "dt-appgw-prod.eastus2.cloudapp.azure.com": "", "signin.att.com": "clcontent.att.com", "clcontent.att.com": "", "scripts.webcontentassessor.com": "k3.shared.global.fastly.net", "k3.shared.global.fastly.net": "", "aa.agkn.com": "ActivationEdge-activation-1631408035.eu-central-1.elb.amazonaws.com", "ActivationEdge-activation-1631408035.eu-central-1.elb.amazonaws.com": "", "ib.adnxs.com": "xandr-g-geo.trafficmanager.net", "xandr-g-geo.trafficmanager.net": "ib.anycast.adnxs.com", "ib.anycast.adnxs.com": "", "idsync.rlcdn.com": "", "cm.g.doubleclick.net": "", "analytics.twitter.com": "ads.twitter.com", "ads.twitter.com": "s.twitter.com", "s.twitter.com": "", "ml314.com": "", "s.amazon-adsystem.com": "", "684dd325.akstat.io": "wildcard46.akstat.io.edgekey.net", "wildcard46.akstat.io.edgekey.net": "e4518.dscx.akamaiedge.net", "e4518.dscx.akamaiedge.net": "", "fonts.gstatic.com": "", "s0.2mdn.net": "", "analytics.foresee.com": "ab1cbac537de54f43b214b172032a880-1825732961.us-east-1.elb.amazonaws.com", "www.google.lu": "", "insight.adsrvr.org": "", "trkn.us": "", "adservice.google.com": "", "pubads.g.doubleclick.net": ""}